{
	"info": {
		"_postman_id": "90944149-a7f8-4a2b-bb19-15b92e418a74",
		"name": "curso-especialista-spring-rest",
		"schema": "https://schema.getpostman.com/json/collection/v2.1.0/collection.json"
	},
	"item": [
		{
			"name": "Github",
			"request": {
				"method": "GET",
				"header": [],
				"url": {
					"raw": "api.github.com/users/danilogmoura/repos",
					"host": [
						"api",
						"github",
						"com"
					],
					"path": [
						"users",
						"danilogmoura",
						"repos"
					]
				}
			},
			"response": []
		},
		{
			"name": "localhost:8080/cozinhas",
			"request": {
				"method": "GET",
				"header": [],
				"url": {
					"raw": "localhost:8080/cozinhas",
					"host": [
						"localhost"
					],
					"port": "8080",
					"path": [
						"cozinhas"
					]
				}
			},
			"response": []
		}
	]
}